quark/proxy.py
quark/app/__init__.py
quark/app/_code.py
quark/app/_db.py
quark/app/_dp.py
quark/app/_recipe.py
quark/app/_studio.py
quark/app/_task.py
quark/app/_viewer.py
quark/dag/__init__.py
quark/dag/executor.py
quark/dag/graph.py
quark/dag/scheduler.py
quark/interface/__init__.py
quark/interface/base.py
quark/interface/qiskit.py
quark/interface/systemq.py
quark/runtime/__init__.py
quark/runtime/assembler.py
quark/runtime/calculator.py
quark/runtime/device.py
quark/runtime/processor.py
quark/runtime/router.py
vios-3.8.2.dist-info/licenses/LICENSE
vios-3.8.2.dist-info/METADATA
vios-3.8.2.dist-info/WHEEL
vios-3.8.2.dist-info/top_level.txt
vios-3.8.2.dist-info/RECORD
