Metadata-Version: 2.4
Name: vios
Version: 3.8.2
Summary: QuarkStudio Runtime
Author-email: YL Feng <fengyl@baqis.ac.cn>
License-Expression: MIT
Project-URL: homepage, https://quarkstudio.readthedocs.io/en/latest
Classifier: Development Status :: 5 - Production/Stable
Classifier: Intended Audience :: Developers
Classifier: Intended Audience :: Science/Research
Classifier: Natural Language :: Chinese (Simplified)
Classifier: Natural Language :: English
Classifier: Operating System :: Microsoft :: Windows
Classifier: Operating System :: POSIX :: Linux
Classifier: Operating System :: MacOS :: MacOS X
Classifier: Programming Language :: Python :: 3.12
Classifier: Topic :: Scientific/Engineering :: Physics
Requires-Python: >=3.12
License-File: LICENSE
Requires-Dist: tqdm
Requires-Dist: rich
Requires-Dist: lmfit
Requires-Dist: sympy
Requires-Dist: zarr
Requires-Dist: loguru
Requires-Dist: jsonschema
Requires-Dist: gitpython
Requires-Dist: paramiko
Requires-Dist: dill
Requires-Dist: itables
Requires-Dist: pandas
Requires-Dist: inset
Requires-Dist: apscheduler
Requires-Dist: networkx
Requires-Dist: qlispc
Dynamic: license-file
